aionx/__init__.py
aionx/base.py
aionx/bootstrap.py
aionx/metrics.py
aionx/models.py
aionx/pipelines.py
aionx/scalers.py
aionx/utils.py
aionx/wrappers.py
aionx/kerasnn/__init__.py
aionx/kerasnn/base.py
aionx/kerasnn/ensemble.py
aionx/kerasnn/losses.py
aionx/kerasnn/trainers.py
aionx/kerasnn/utils.py
aionx-2.0.0.dist-info/LICENSE
aionx-2.0.0.dist-info/METADATA
aionx-2.0.0.dist-info/WHEEL
aionx-2.0.0.dist-info/top_level.txt
aionx-2.0.0.dist-info/RECORD
