Metadata-Version: 2.1
Name: aionx
Version: 2.0.0
Summary: Library for designing Machine Learning models for time series forecast
Author: Mikael Frenette
Author-email: <mik.frenette@gmail.com>
License-File: LICENSE
Requires-Dist: numpy
Requires-Dist: pandas
Requires-Dist: tensorflow
Requires-Dist: scikit-learn
